LICENSE
README.md
setup.cfg
setup.py
py_maori_stemmer/__init__.py
py_maori_stemmer/among.py
py_maori_stemmer/basestemmer.py
py_maori_stemmer/maori.py
py_maori_stemmer.egg-info/PKG-INFO
py_maori_stemmer.egg-info/SOURCES.txt
py_maori_stemmer.egg-info/dependency_links.txt
py_maori_stemmer.egg-info/top_level.txt
tests/__init__.py
tests/test_maori.py