Metadata-Version: 2.1
Name: py-maori-stemmer
Version: 0.0.3
Summary: Stemmer for Maori language
Home-page: https://github.com/fzyukio/py-maori-stemmer
Author: Yukio Fukuzawa
Author-email: nishinokaze8@gmail.com
License: UNKNOWN
Platform: UNKNOWN
Classifier: Programming Language :: Python :: 3
Classifier: License :: OSI Approved :: MIT License
Classifier: Operating System :: OS Independent
License-File: LICENSE
